constants_and_utils/__init__.py
constants_and_utils/constants/__init__.py
constants_and_utils/constants/enums.py
constants_and_utils/constants/responses.py
constants_and_utils/utils/__init__.py
constants_and_utils/utils/contract.py
constants_and_utils/utils/decorators.py
constants_and_utils/utils/helpers.py
constants_and_utils/utils/mongoengine.py
constants_and_utils/utils/use_cases.py
constants_and_utils/utils/validator/__init__.py
constants_and_utils/utils/validator/basevalidator.py
constants_and_utils/utils/validator/validator_mongoengine.py
tests/__init__.py
tests/constants/__init__.py
tests/constants/test_enums.py
tests/utils/__init__.py
tests/utils/test_decorators.py
tests/utils/test_helpers.py
tests/utils/test_mongoengine.py
tests/utils/test_use_cases.py
tests/utils/validator/__init__.py
tests/utils/validator/test_base_validator.py
tests/utils/validator/test_mongo_validator.py
constants_and_utils-0.0.5.dist-info/LICENSE
constants_and_utils-0.0.5.dist-info/METADATA
constants_and_utils-0.0.5.dist-info/WHEEL
constants_and_utils-0.0.5.dist-info/top_level.txt
constants_and_utils-0.0.5.dist-info/RECORD
