Metadata-Version: 2.1
Name: constants-and-utils
Version: 0.0.5
Summary: Constants and utils
Home-page: https://gitlab.com/terminus-zinobe/constants-and-utils
Author: Terminus
Author-email: jose.salas@zinobe.com
License: UNKNOWN
Platform: UNKNOWN
Classifier: Programming Language :: Python :: 3
Classifier: License :: OSI Approved :: MIT License
Classifier: Operating System :: OS Independent
Requires-Python: >=3.6
Provides-Extra: mongoengine
Requires-Dist: mongoengine (>=0.18.2) ; extra == 'mongoengine'
Requires-Dist: Cerberus (>=1.3.2) ; extra == 'mongoengine'
Requires-Dist: pymongo (>=3.10.1) ; extra == 'mongoengine'
Requires-Dist: deepdiff (>=4.3.2) ; extra == 'mongoengine'
Requires-Dist: mongomock (==3.20.0) ; extra == 'mongoengine'
